{
  "$schema": "https://schema.management.azure.com/schemas/2015-01-01/deploymentTemplate.json",
  "contentVersion": "1.0.0.0",
  "parameters": {
    "workspaceName": {
      "type": "string",
      "metadata": {
        "description": "Assign a name for the Log Analytic Workspace Name"
      }
    },
    "workspaceRegion": {
      "type": "string",
      "defaultValue": "West Europe",
      "allowedValues": [
        "Australia Southeast",
        "East US",
        "Japan East",
        "Southeast Asia",
        "UK South",
        "West Central US",
        "West Europe",
        "North Europe"
      ],
      "metadata": {
        "description": "Specify the region for your Workspace"
      }
    },
    "automationAccountName": {
      "type": "string",
      "metadata": {
        "description": "Assign a name for the Automation account"
      }
    },
    "automationRegion": {
      "type": "string",
      "defaultValue": "West Europe",
      "allowedValues": [
        "Japan East",
        "East US 2",
        "West Europe",
        "Southeast Asia",
        "South Central US",
        "North Europe",
        "Canada Central",
        "Australia Southeast",
        "Central India",
        "Japan East"
      ],
      "metadata": {
        "description": "Specify the region for your Automation account"
      }
    },
    "_artifactsLocation": {
      "type": "string",
      "defaultValue": "https://raw.githubusercontent.com/Azure/azure-quickstart-templates/master/oms-all-deploy",
      "metadata": {
        "description": "The base URI where artifacts required by this template are located"
      }
    },
    "azureAdmin": {
      "type": "string",
      "metadata": {
        "description": "Enter your service admin user"
      }
    },
    "azureAdminPwd": {
      "type": "securestring",
      "metadata": {
        "description": "Enter the pwd for the service admin user. The pwd is enrypted during runtime and in the Automation assets"
      }
    }
  },
  "variables": {
    "nestedTemplates": {
      "automation": "[concat(parameters('_artifactsLocation'), '/nestedtemplates/automation.json')]",
      "workspace": "[concat(parameters('_artifactsLocation'), '/nestedtemplates/workspace.json')]"
    }
  },
  "resources": [
    {
      "type": "Microsoft.Resources/deployments",
      "apiVersion": "2016-02-01",
      "name": "workspace",
      "properties": {
        "mode": "Incremental",
        "templateLink": {
          "uri": "[variables('nestedTemplates').workspace]",
          "contentVersion": "1.0.0.0"
        },
        "parameters": {
          "workspaceName": {
            "value": "[parameters('workspaceName')]"
          },
          "workspaceRegion": {
            "value": "[parameters('workspaceRegion')]"
          }
        }
      }
    },
    {
      "type": "Microsoft.Resources/deployments",
      "apiVersion": "2016-02-01",
      "name": "automation",
      "dependsOn": [
        "[concat('Microsoft.Resources/deployments/', 'workspace')]"
      ],
      "properties": {
        "mode": "Incremental",
        "templateLink": {
          "uri": "[variables('nestedTemplates').automation]",
          "contentVersion": "1.0.0.0"
        },
        "parameters": {
          "automationAccountName": {
            "value": "[parameters('automationAccountName')]"
          },
          "automationRegion": {
            "value": "[parameters('automationRegion')]"
          },
          "workspaceName": {
            "value": "[parameters('workspaceName')]"
          },
          "azureAdmin": {
            "value": "[parameters('azureAdmin')]"
          },
          "azureAdminPwd": {
            "value": "[parameters('azureAdminPwd')]"
          }
        }
      }
    }
  ],
  "outputs": { }
}